SparkLunwenDaxingJiqunShangDeKuaisuHeTongyongShujuchuliJiagouXiuzhengban/README.md
SparkLunwenDaxingJiqunShangDeKuaisuHeTongyongShujuchuliJiagouXiuzhengban/__init__.py
SparkLunwenDaxingJiqunShangDeKuaisuHeTongyongShujuchuliJiagouXiuzhengban/__main__.py
SparkLunwenDaxingJiqunShangDeKuaisuHeTongyongShujuchuliJiagouXiuzhengban/file.pdf
SparkLunwenDaxingJiqunShangDeKuaisuHeTongyongShujuchuliJiagouXiuzhengban/index.html
spark_lunwen_daxing_jiqun_shang_de_kuaisu_he_tongyong_shujuchuli_jiagou_xiuzhengban-2024.3.2.0.dist-info/METADATA
spark_lunwen_daxing_jiqun_shang_de_kuaisu_he_tongyong_shujuchuli_jiagou_xiuzhengban-2024.3.2.0.dist-info/WHEEL
spark_lunwen_daxing_jiqun_shang_de_kuaisu_he_tongyong_shujuchuli_jiagou_xiuzhengban-2024.3.2.0.dist-info/entry_points.txt
spark_lunwen_daxing_jiqun_shang_de_kuaisu_he_tongyong_shujuchuli_jiagou_xiuzhengban-2024.3.2.0.dist-info/top_level.txt
spark_lunwen_daxing_jiqun_shang_de_kuaisu_he_tongyong_shujuchuli_jiagou_xiuzhengban-2024.3.2.0.dist-info/RECORD
