Metadata-Version: 2.1
Name: spark-lunwen-daxing-jiqun-shang-de-kuaisu-he-tongyong-shujuchuli-jiagou-xiuzhengban
Version: 2024.3.2.0
Summary: 【spark论文】大型集群上的快速和通用数据处理架构（修正版）
Home-page: https://github.com/apachecn/spark-lunwen-daxing-jiqun-shang-de-kuaisu-he-tongyong-shujuchuli-jiagou-xiuzhengban
Author: ApacheCN
Author-email: apachecn@163.com
License: UNKNOWN
Platform: UNKNOWN
Classifier: Development Status :: 4 - Beta
Classifier: Environment :: Console
Classifier: Intended Audience :: Developers
Classifier: Intended Audience :: End Users/Desktop
Classifier: License :: Other/Proprietary License
Classifier: Natural Language :: Chinese (Simplified)
Classifier: Natural Language :: English
Classifier: Operating System :: OS Independent
Classifier: Programming Language :: Python :: 3
Classifier: Programming Language :: Python :: 3 :: Only
Classifier: Programming Language :: Python :: 3.6
Classifier: Programming Language :: Python :: 3.7
Classifier: Topic :: Text Processing :: Markup :: Markdown
Classifier: Topic :: Text Processing :: Markup :: HTML
Classifier: Topic :: Internet :: WWW/HTTP
Classifier: Topic :: Software Development :: Documentation
Classifier: Topic :: Documentation
Requires-Python: >=3.6
